pollination/imageless_annual_glare/__init__.py
pollination/imageless_annual_glare/_postprocess.py
pollination/imageless_annual_glare/_prepare_folder.py
pollination/imageless_annual_glare/_raytracing.py
pollination/imageless_annual_glare/entry.py
pollination_imageless_annual_glare-0.1.8.dist-info/LICENSE
pollination_imageless_annual_glare-0.1.8.dist-info/METADATA
pollination_imageless_annual_glare-0.1.8.dist-info/WHEEL
pollination_imageless_annual_glare-0.1.8.dist-info/top_level.txt
pollination_imageless_annual_glare-0.1.8.dist-info/RECORD
